{
    "6825": "https://thailand-real.estate/property/o6825/",
    "21153": "https://thailand-real.estate/property/o21153/",
    "22522": "https://thailand-real.estate/property/o22522/",
    "59519": "https://thailand-real.estate/property/o59519/",
    "23271": "https://thailand-real.estate/property/o23271/",
    "101066": "https://thailand-real.estate/property/o101066/",
    "6349": "https://thailand-real.estate/property/o6349/",
    "20138": "https://thailand-real.estate/property/o20138/",
    "22907": "https://thailand-real.estate/property/o22907/",
    "23700": "https://thailand-real.estate/property/o23700/",
    "23265": "https://thailand-real.estate/property/o23265/",
    "22527": "https://thailand-real.estate/property/o22527/",
    "21427": "https://thailand-real.estate/property/o21427/",
    "19966": "https://thailand-real.estate/property/o19966/",
    "6346": "https://thailand-real.estate/property/o6346/",
    "46987": "https://thailand-real.estate/property/o46987/",
    "59522": "https://thailand-real.estate/property/o59522/",
    "45005": "https://thailand-real.estate/property/o45005/",
    "24239": "https://thailand-real.estate/property/o24239/",
    "6342": "https://thailand-real.estate/property/o6342/",
    "20248": "https://thailand-real.estate/property/o20248/",
    "6347": "https://thailand-real.estate/property/o6347/",
    "20008": "https://thailand-real.estate/property/o20008/",
    "6348": "https://thailand-real.estate/property/o6348/",
    "83579": "https://thailand-real.estate/property/o83579/",
    "23393": "https://thailand-real.estate/property/o23393/",
    "20458": "https://thailand-real.estate/property/o20458/",
    "22231": "https://thailand-real.estate/property/o22231/",
    "23281": "https://thailand-real.estate/property/o23281/",
    "21905": "https://thailand-real.estate/property/o21905/",
    "23284": "https://thailand-real.estate/property/o23284/",
    "23926": "https://thailand-real.estate/property/o23926/",
    "20224": "https://thailand-real.estate/property/o20224/",
    "23852": "https://thailand-real.estate/property/o23852/",
    "24258": "https://thailand-real.estate/property/o24258/",
    "21188": "https://thailand-real.estate/property/o21188/",
    "82564": "https://thailand-real.estate/property/o82564/",
    "20617": "https://thailand-real.estate/property/o20617/",
    "23104": "https://thailand-real.estate/property/o23104/",
    "5973": "https://thailand-real.estate/property/o5973/",
    "21467": "https://thailand-real.estate/property/o21467/",
    "22937": "https://thailand-real.estate/property/o22937/",
    "20376": "https://thailand-real.estate/property/o20376/",
    "22995": "https://thailand-real.estate/property/o22995/",
    "24117": "https://thailand-real.estate/property/o24117/",
    "45392": "https://thailand-real.estate/property/o45392/",
    "45510": "https://thailand-real.estate/property/o45510/",
    "20481": "https://thailand-real.estate/property/o20481/",
    "45551": "https://thailand-real.estate/property/o45551/",
    "22672": "https://thailand-real.estate/property/o22672/",
    "22151": "https://thailand-real.estate/property/o22151/",
    "5978": "https://thailand-real.estate/property/o5978/",
    "5975": "https://thailand-real.estate/property/o5975/",
    "5977": "https://thailand-real.estate/property/o5977/",
    "19726": "https://thailand-real.estate/property/o19726/",
    "20476": "https://thailand-real.estate/property/o20476/",
    "19959": "https://thailand-real.estate/property/o19959/",
    "73539": "https://thailand-real.estate/property/o73539/",
    "26617": "https://thailand-real.estate/property/o26617/",
    "23500": "https://thailand-real.estate/property/o23500/",
    "22336": "https://thailand-real.estate/property/o22336/",
    "21284": "https://thailand-real.estate/property/o21284/",
    "22637": "https://thailand-real.estate/property/o22637/",
    "23743": "https://thailand-real.estate/property/o23743/",
    "19714": "https://thailand-real.estate/property/o19714/",
    "22317": "https://thailand-real.estate/property/o22317/",
    "21640": "https://thailand-real.estate/property/o21640/",
    "6341": "https://thailand-real.estate/property/o6341/",
    "23017": "https://thailand-real.estate/property/o23017/",
    "20934": "https://thailand-real.estate/property/o20934/",
    "27212": "https://thailand-real.estate/property/o27212/",
    "20280": "https://thailand-real.estate/property/o20280/",
    "21864": "https://thailand-real.estate/property/o21864/",
    "21190": "https://thailand-real.estate/property/o21190/",
    "19755": "https://thailand-real.estate/property/o19755/",
    "24061": "https://thailand-real.estate/property/o24061/",
    "23276": "https://thailand-real.estate/property/o23276/",
    "20671": "https://thailand-real.estate/property/o20671/",
    "83580": "https://thailand-real.estate/property/o83580/",
    "23468": "https://thailand-real.estate/property/o23468/",
    "23335": "https://thailand-real.estate/property/o23335/",
    "24298": "https://thailand-real.estate/property/o24298/",
    "23180": "https://thailand-real.estate/property/o23180/",
    "22563": "https://thailand-real.estate/property/o22563/",
    "24094": "https://thailand-real.estate/property/o24094/",
    "24299": "https://thailand-real.estate/property/o24299/",
    "20000": "https://thailand-real.estate/property/o20000/",
    "21273": "https://thailand-real.estate/property/o21273/",
    "21187": "https://thailand-real.estate/property/o21187/",
    "26548": "https://thailand-real.estate/property/o26548/",
    "20711": "https://thailand-real.estate/property/o20711/",
    "5974": "https://thailand-real.estate/property/o5974/",
    "21938": "https://thailand-real.estate/property/o21938/",
    "22495": "https://thailand-real.estate/property/o22495/",
    "21988": "https://thailand-real.estate/property/o21988/",
    "23905": "https://thailand-real.estate/property/o23905/",
    "22152": "https://thailand-real.estate/property/o22152/",
    "23580": "https://thailand-real.estate/property/o23580/",
    "23474": "https://thailand-real.estate/property/o23474/",
    "24188": "https://thailand-real.estate/property/o24188/",
    "23175": "https://thailand-real.estate/property/o23175/",
    "24111": "https://thailand-real.estate/property/o24111/",
    "21834": "https://thailand-real.estate/property/o21834/",
    "23701": "https://thailand-real.estate/property/o23701/",
    "23938": "https://thailand-real.estate/property/o23938/",
    "45456": "https://thailand-real.estate/property/o45456/",
    "23297": "https://thailand-real.estate/property/o23297/",
    "19738": "https://thailand-real.estate/property/o19738/",
    "19943": "https://thailand-real.estate/property/o19943/",
    "23355": "https://thailand-real.estate/property/o23355/",
    "23999": "https://thailand-real.estate/property/o23999/",
    "83581": "https://thailand-real.estate/property/o83581/",
    "23705": "https://thailand-real.estate/property/o23705/",
    "23706": "https://thailand-real.estate/property/o23706/",
    "23767": "https://thailand-real.estate/property/o23767/",
    "19772": "https://thailand-real.estate/property/o19772/",
    "101065": "https://thailand-real.estate/property/pristine-park-3-101065/",
    "21186": "https://thailand-real.estate/property/o21186/",
    "23442": "https://thailand-real.estate/property/o23442/",
    "19994": "https://thailand-real.estate/property/o19994/",
    "20143": "https://thailand-real.estate/property/o20143/",
    "5976": "https://thailand-real.estate/property/o5976/",
    "24160": "https://thailand-real.estate/property/o24160/",
    "20970": "https://thailand-real.estate/property/o20970/",
    "22148": "https://thailand-real.estate/property/o22148/",
    "6344": "https://thailand-real.estate/property/o6344/",
    "24332": "https://thailand-real.estate/property/o24332/",
    "45559": "https://thailand-real.estate/property/o45559/",
    "23326": "https://thailand-real.estate/property/o23326/",
    "20334": "https://thailand-real.estate/property/o20334/",
    "22789": "https://thailand-real.estate/property/o22789/",
    "23016": "https://thailand-real.estate/property/o23016/",
    "22896": "https://thailand-real.estate/property/o22896/",
    "22631": "https://thailand-real.estate/property/o22631/",
    "23851": "https://thailand-real.estate/property/o23851/",
    "23539": "https://thailand-real.estate/property/o23539/",
    "22149": "https://thailand-real.estate/property/o22149/",
    "20506": "https://thailand-real.estate/property/o20506/",
    "20111": "https://thailand-real.estate/property/o20111/",
    "23499": "https://thailand-real.estate/property/o23499/",
    "24238": "https://thailand-real.estate/property/o24238/",
    "20385": "https://thailand-real.estate/property/o20385/",
    "21168": "https://thailand-real.estate/property/o21168/",
    "21283": "https://thailand-real.estate/property/o21283/",
    "24300": "https://thailand-real.estate/property/o24300/",
    "23404": "https://thailand-real.estate/property/o23404/",
    "20708": "https://thailand-real.estate/property/o20708/",
    "23590": "https://thailand-real.estate/property/o23590/",
    "20361": "https://thailand-real.estate/property/o20361/",
    "21043": "https://thailand-real.estate/property/o21043/",
    "24244": "https://thailand-real.estate/property/o24244/",
    "21615": "https://thailand-real.estate/property/o21615/",
    "22170": "https://thailand-real.estate/property/o22170/",
    "23842": "https://thailand-real.estate/property/o23842/",
    "20595": "https://thailand-real.estate/property/o20595/",
    "20262": "https://thailand-real.estate/property/o20262/",
    "23128": "https://thailand-real.estate/property/o23128/",
    "20266": "https://thailand-real.estate/property/o20266/",
    "24150": "https://thailand-real.estate/property/o24150/",
    "45061": "https://thailand-real.estate/property/o45061/",
    "45224": "https://thailand-real.estate/property/o45224/",
    "20965": "https://thailand-real.estate/property/o20965/",
    "22321": "https://thailand-real.estate/property/o22321/",
    "23704": "https://thailand-real.estate/property/o23704/",
    "21069": "https://thailand-real.estate/property/o21069/",
    "23210": "https://thailand-real.estate/property/o23210/",
    "23294": "https://thailand-real.estate/property/o23294/",
    "26374": "https://thailand-real.estate/property/seven-seas-cote-dazur-28818/o26374/",
    "26342": "https://thailand-real.estate/property/o26342/",
    "21743": "https://thailand-real.estate/property/o21743/",
    "23868": "https://thailand-real.estate/property/o23868/",
    "19744": "https://thailand-real.estate/property/o19744/",
    "23843": "https://thailand-real.estate/property/o23843/",
    "23566": "https://thailand-real.estate/property/o23566/",
    "20109": "https://thailand-real.estate/property/o20109/",
    "24187": "https://thailand-real.estate/property/o24187/",
    "24134": "https://thailand-real.estate/property/o24134/",
    "24049": "https://thailand-real.estate/property/o24049/",
    "23841": "https://thailand-real.estate/property/o23841/",
    "21936": "https://thailand-real.estate/property/o21936/",
    "22812": "https://thailand-real.estate/property/o22812/",
    "23279": "https://thailand-real.estate/property/o23279/",
    "22638": "https://thailand-real.estate/property/o22638/",
    "23928": "https://thailand-real.estate/property/o23928/",
    "22418": "https://thailand-real.estate/property/o22418/",
    "22040": "https://thailand-real.estate/property/o22040/",
    "73542": "https://thailand-real.estate/property/o73542/",
    "26906": "https://thailand-real.estate/property/o26906/",
    "20258": "https://thailand-real.estate/property/o20258/",
    "19954": "https://thailand-real.estate/property/o19954/",
    "23274": "https://thailand-real.estate/property/o23274/",
    "23844": "https://thailand-real.estate/property/o23844/",
    "20176": "https://thailand-real.estate/property/o20176/",
    "22659": "https://thailand-real.estate/property/o22659/",
    "21707": "https://thailand-real.estate/property/o21707/",
    "23745": "https://thailand-real.estate/property/o23745/",
    "20749": "https://thailand-real.estate/property/o20749/",
    "21028": "https://thailand-real.estate/property/o21028/",
    "24152": "https://thailand-real.estate/property/o24152/",
    "20510": "https://thailand-real.estate/property/o20510/",
    "23498": "https://thailand-real.estate/property/o23498/",
    "23325": "https://thailand-real.estate/property/o23325/",
    "24151": "https://thailand-real.estate/property/o24151/",
    "20507": "https://thailand-real.estate/property/o20507/",
    "20199": "https://thailand-real.estate/property/o20199/",
    "24095": "https://thailand-real.estate/property/o24095/",
    "19796": "https://thailand-real.estate/property/o19796/",
    "23353": "https://thailand-real.estate/property/o23353/",
    "23789": "https://thailand-real.estate/property/o23789/",
    "24294": "https://thailand-real.estate/property/o24294/",
    "26214": "https://thailand-real.estate/property/o26214/",
    "23696": "https://thailand-real.estate/property/o23696/",
    "20750": "https://thailand-real.estate/property/o20750/",
    "21417": "https://thailand-real.estate/property/o21417/",
    "22675": "https://thailand-real.estate/property/o22675/",
    "23088": "https://thailand-real.estate/property/o23088/",
    "26368": "https://thailand-real.estate/property/o26368/",
    "19837": "https://thailand-real.estate/property/o19837/",
    "20742": "https://thailand-real.estate/property/o20742/",
    "23678": "https://thailand-real.estate/property/o23678/",
    "24105": "https://thailand-real.estate/property/o24105/",
    "83593": "https://thailand-real.estate/property/o83593/",
    "20821": "https://thailand-real.estate/property/o20821/",
    "21379": "https://thailand-real.estate/property/o21379/",
    "22685": "https://thailand-real.estate/property/o22685/",
    "23574": "https://thailand-real.estate/property/o23574/",
    "22641": "https://thailand-real.estate/property/o22641/",
    "23699": "https://thailand-real.estate/property/o23699/",
    "24459": "https://thailand-real.estate/property/o24459/",
    "45186": "https://thailand-real.estate/property/o45186/",
    "19849": "https://thailand-real.estate/property/o19849/",
    "21314": "https://thailand-real.estate/property/o21314/",
    "23639": "https://thailand-real.estate/property/o23639/",
    "19759": "https://thailand-real.estate/property/o19759/",
    "20110": "https://thailand-real.estate/property/o20110/",
    "22144": "https://thailand-real.estate/property/o22144/",
    "24069": "https://thailand-real.estate/property/o24069/",
    "24149": "https://thailand-real.estate/property/o24149/",
    "24475": "https://thailand-real.estate/property/o24475/",
    "45414": "https://thailand-real.estate/property/o45414/",
    "19902": "https://thailand-real.estate/property/o19902/",
    "21987": "https://thailand-real.estate/property/o21987/",
    "24118": "https://thailand-real.estate/property/o24118/",
    "102287": "https://thailand-real.estate/property/o102287/",
    "27225": "https://thailand-real.estate/property/o27225/",
    "20574": "https://thailand-real.estate/property/o20574/",
    "20681": "https://thailand-real.estate/property/o20681/",
    "23126": "https://thailand-real.estate/property/o23126/",
    "26115": "https://thailand-real.estate/property/o26115/",
    "26219": "https://thailand-real.estate/property/o26219/",
    "27167": "https://thailand-real.estate/property/o27167/",
    "26842": "https://thailand-real.estate/property/o26842/",
    "20362": "https://thailand-real.estate/property/o20362/",
    "45538": "https://thailand-real.estate/property/o45538/",
    "45334": "https://thailand-real.estate/property/o45334/",
    "21767": "https://thailand-real.estate/property/o21767/",
    "45529": "https://thailand-real.estate/property/o45529/",
    "26343": "https://thailand-real.estate/property/o26343/",
    "83595": "https://thailand-real.estate/property/o83595/",
    "23250": "https://thailand-real.estate/property/o23250/",
    "73540": "https://thailand-real.estate/property/o73540/",
    "45378": "https://thailand-real.estate/property/o45378/",
    "45467": "https://thailand-real.estate/property/o45467/",
    "26151": "https://thailand-real.estate/property/o26151/",
    "26192": "https://thailand-real.estate/property/o26192/",
    "26261": "https://thailand-real.estate/property/o26261/",
    "26215": "https://thailand-real.estate/property/o26215/",
    "45185": "https://thailand-real.estate/property/o45185/",
    "26221": "https://thailand-real.estate/property/o26221/",
    "85392": "https://thailand-real.estate/property/o85392/",
    "45498": "https://thailand-real.estate/property/o45498/",
    "45216": "https://thailand-real.estate/property/o45216/",
    "101442": "https://thailand-real.estate/property/o101442/",
    "45494": "https://thailand-real.estate/property/o45494/",
    "45010": "https://thailand-real.estate/property/o45010/",
    "45265": "https://thailand-real.estate/property/o45265/",
    "45300": "https://thailand-real.estate/property/o45300/",
    "45077": "https://thailand-real.estate/property/o45077/",
    "45317": "https://thailand-real.estate/property/o45317/",
    "53838": "https://thailand-real.estate/property/o53838/",
    "45307": "https://thailand-real.estate/property/o45307/",
    "45030": "https://thailand-real.estate/property/o45030/",
    "45545": "https://thailand-real.estate/property/o45545/",
    "45187": "https://thailand-real.estate/property/o45187/",
    "45031": "https://thailand-real.estate/property/o45031/",
    "83578": "https://thailand-real.estate/property/o83578/",
    "45279": "https://thailand-real.estate/property/o45279/",
    "101068": "https://thailand-real.estate/property/o101068/",
    "83565": "https://thailand-real.estate/property/o83565/",
    "45251": "https://thailand-real.estate/property/o45251/",
    "45495": "https://thailand-real.estate/property/o45495/",
    "45473": "https://thailand-real.estate/property/o45473/",
    "45146": "https://thailand-real.estate/property/o45146/",
    "45286": "https://thailand-real.estate/property/o45286/",
    "45413": "https://thailand-real.estate/property/o45413/",
    "45674": "https://thailand-real.estate/property/grande-caribbean-28922/o45674/",
    "73541": "https://thailand-real.estate/property/o73541/",
    "45513": "https://thailand-real.estate/property/o45513/",
    "82567": "https://thailand-real.estate/property/o82567/",
    "45352": "https://thailand-real.estate/property/o45352/",
    "45159": "https://thailand-real.estate/property/o45159/",
    "45144": "https://thailand-real.estate/property/o45144/",
    "45296": "https://thailand-real.estate/property/o45296/",
    "83594": "https://thailand-real.estate/property/o83594/",
    "45255": "https://thailand-real.estate/property/o45255/",
    "85395": "https://thailand-real.estate/property/o85395/",
    "100376": "https://thailand-real.estate/property/o100376/",
    "45532": "https://thailand-real.estate/property/o45532/",
    "45196": "https://thailand-real.estate/property/o45196/",
    "45479": "https://thailand-real.estate/property/o45479/",
    "45368": "https://thailand-real.estate/property/o45368/",
    "45379": "https://thailand-real.estate/property/o45379/",
    "45084": "https://thailand-real.estate/property/o45084/",
    "45074": "https://thailand-real.estate/property/o45074/",
    "45153": "https://thailand-real.estate/property/o45153/",
    "101434": "https://thailand-real.estate/property/o101434/",
    "45371": "https://thailand-real.estate/property/o45371/",
    "45398": "https://thailand-real.estate/property/o45398/",
    "45177": "https://thailand-real.estate/property/o45177/",
    "45440": "https://thailand-real.estate/property/o45440/",
    "45068": "https://thailand-real.estate/property/o45068/",
    "45235": "https://thailand-real.estate/property/o45235/",
    "83568": "https://thailand-real.estate/property/o83568/",
    "45229": "https://thailand-real.estate/property/o45229/",
    "45306": "https://thailand-real.estate/property/o45306/",
    "45302": "https://thailand-real.estate/property/o45302/",
    "45322": "https://thailand-real.estate/property/o45322/",
    "45060": "https://thailand-real.estate/property/o45060/",
    "45308": "https://thailand-real.estate/property/o45308/",
    "45367": "https://thailand-real.estate/property/o45367/",
    "45408": "https://thailand-real.estate/property/o45408/",
    "45065": "https://thailand-real.estate/property/o45065/",
    "45297": "https://thailand-real.estate/property/o45297/",
    "45502": "https://thailand-real.estate/property/o45502/",
    "45316": "https://thailand-real.estate/property/o45316/",
    "45019": "https://thailand-real.estate/property/o45019/",
    "45048": "https://thailand-real.estate/property/o45048/",
    "83626": "https://thailand-real.estate/property/o83626/",
    "54697": "https://thailand-real.estate/property/o54697/",
    "45066": "https://thailand-real.estate/property/o45066/",
    "101279": "https://thailand-real.estate/property/o101279/",
    "53787": "https://thailand-real.estate/property/o53787/",
    "45173": "https://thailand-real.estate/property/o45173/",
    "45018": "https://thailand-real.estate/property/o45018/",
    "57486": "https://thailand-real.estate/property/o57486/",
    "53715": "https://thailand-real.estate/property/o53715/",
    "45310": "https://thailand-real.estate/property/o45310/",
    "45301": "https://thailand-real.estate/property/o45301/",
    "105118": "https://thailand-real.estate/property/o105118/",
    "53726": "https://thailand-real.estate/property/o53726/",
    "83569": "https://thailand-real.estate/property/o83569/",
    "73548": "https://thailand-real.estate/property/o73548/",
    "47417": "https://thailand-real.estate/property/o47417/",
    "47423": "https://thailand-real.estate/property/o47423/",
    "101821": "https://thailand-real.estate/property/o101821/",
    "45017": "https://thailand-real.estate/property/o45017/",
    "73934": "https://thailand-real.estate/property/o73934/",
    "82584": "https://thailand-real.estate/property/o82584/",
    "71649": "https://thailand-real.estate/property/o71649/",
    "104742": "https://thailand-real.estate/property/o104742/",
    "100694": "https://thailand-real.estate/property/o100694/",
    "73546": "https://thailand-real.estate/property/o73546/",
    "73550": "https://thailand-real.estate/property/o73550/",
    "83567": "https://thailand-real.estate/property/o83567/",
    "73545": "https://thailand-real.estate/property/o73545/",
    "73549": "https://thailand-real.estate/property/o73549/",
    "82559": "https://thailand-real.estate/property/o82559/",
    "101070": "https://thailand-real.estate/property/o101070/",
    "57591": "https://thailand-real.estate/property/seven-seas-cote-dazur-28818/o57591/",
    "53753": "https://thailand-real.estate/property/o53753/",
    "82493": "https://thailand-real.estate/property/o82493/",
    "73931": "https://thailand-real.estate/property/o73931/",
    "73568": "https://thailand-real.estate/property/o73568/",
    "73569": "https://thailand-real.estate/property/o73569/",
    "73930": "https://thailand-real.estate/property/o73930/",
    "101454": "https://thailand-real.estate/property/o101454/",
    "73926": "https://thailand-real.estate/property/o73926/",
    "63248": "https://thailand-real.estate/property/cosy-beach-view-29182/o63248/",
    "53703": "https://thailand-real.estate/property/o53703/",
    "101256": "https://thailand-real.estate/property/o101256/",
    "53702": "https://thailand-real.estate/property/o53702/",
    "82513": "https://thailand-real.estate/property/o82513/",
    "82556": "https://thailand-real.estate/property/o82556/",
    "82627": "https://thailand-real.estate/property/o82627/",
    "57592": "https://thailand-real.estate/property/seven-seas-cote-dazur-28818/o57592/",
    "53801": "https://thailand-real.estate/property/o53801/",
    "82500": "https://thailand-real.estate/property/o82500/",
    "82589": "https://thailand-real.estate/property/o82589/",
    "101069": "https://thailand-real.estate/property/o101069/",
    "73547": "https://thailand-real.estate/property/o73547/",
    "82617": "https://thailand-real.estate/property/o82617/",
    "101419": "https://thailand-real.estate/property/o101419/",
    "73928": "https://thailand-real.estate/property/o73928/",
    "73932": "https://thailand-real.estate/property/o73932/",
    "82476": "https://thailand-real.estate/property/o82476/",
    "82511": "https://thailand-real.estate/property/o82511/",
    "82519": "https://thailand-real.estate/property/o82519/",
    "101453": "https://thailand-real.estate/property/o101453/",
    "101067": "https://thailand-real.estate/property/o101067/",
    "82482": "https://thailand-real.estate/property/o82482/",
    "53789": "https://thailand-real.estate/property/o53789/",
    "73566": "https://thailand-real.estate/property/o73566/",
    "82558": "https://thailand-real.estate/property/o82558/",
    "82478": "https://thailand-real.estate/property/o82478/",
    "101527": "https://thailand-real.estate/property/o101527/",
    "84801": "https://thailand-real.estate/property/o84801/",
    "82790": "https://thailand-real.estate/property/o82790/",
    "82773": "https://thailand-real.estate/property/o82773/",
    "73567": "https://thailand-real.estate/property/o73567/",
    "73933": "https://thailand-real.estate/property/o73933/",
    "82624": "https://thailand-real.estate/property/o82624/",
    "101451": "https://thailand-real.estate/property/o101451/",
    "101071": "https://thailand-real.estate/property/o101071/",
    "100206": "https://thailand-real.estate/property/o100206/",
    "81232": "https://thailand-real.estate/property/o81232/",
    "82613": "https://thailand-real.estate/property/o82613/",
    "82514": "https://thailand-real.estate/property/o82514/",
    "101312": "https://thailand-real.estate/property/o101312/",
    "81819": "https://thailand-real.estate/property/o81819/",
    "100273": "https://thailand-real.estate/property/o100273/",
    "82640": "https://thailand-real.estate/property/o82640/",
    "82536": "https://thailand-real.estate/property/o82536/",
    "82540": "https://thailand-real.estate/property/o82540/",
    "82512": "https://thailand-real.estate/property/o82512/",
    "82492": "https://thailand-real.estate/property/o82492/",
    "106807": "https://thailand-real.estate/property/o106807/",
    "82771": "https://thailand-real.estate/property/o82771/",
    "82758": "https://thailand-real.estate/property/o82758/",
    "82696": "https://thailand-real.estate/property/o82696/",
    "82612": "https://thailand-real.estate/property/o82612/",
    "82618": "https://thailand-real.estate/property/o82618/",
    "82499": "https://thailand-real.estate/property/o82499/",
    "100370": "https://thailand-real.estate/property/o100370/",
    "82801": "https://thailand-real.estate/property/o82801/",
    "82799": "https://thailand-real.estate/property/o82799/",
    "82760": "https://thailand-real.estate/property/o82760/",
    "82767": "https://thailand-real.estate/property/o82767/",
    "82770": "https://thailand-real.estate/property/o82770/",
    "82772": "https://thailand-real.estate/property/o82772/",
    "82723": "https://thailand-real.estate/property/o82723/",
    "82526": "https://thailand-real.estate/property/o82526/",
    "82708": "https://thailand-real.estate/property/o82708/",
    "82694": "https://thailand-real.estate/property/o82694/",
    "82625": "https://thailand-real.estate/property/o82625/",
    "82497": "https://thailand-real.estate/property/o82497/",
    "100195": "https://thailand-real.estate/property/o100195/",
    "82642": "https://thailand-real.estate/property/o82642/",
    "82796": "https://thailand-real.estate/property/o82796/",
    "82768": "https://thailand-real.estate/property/o82768/",
    "82621": "https://thailand-real.estate/property/o82621/",
    "82639": "https://thailand-real.estate/property/o82639/",
    "82498": "https://thailand-real.estate/property/o82498/",
    "82591": "https://thailand-real.estate/property/o82591/",
    "101461": "https://thailand-real.estate/property/o101461/",
    "101481": "https://thailand-real.estate/property/o101481/",
    "82797": "https://thailand-real.estate/property/o82797/",
    "100293": "https://thailand-real.estate/property/o100293/",
    "82538": "https://thailand-real.estate/property/o82538/",
    "58977": "https://thailand-real.estate/property/o58977/",
    "82477": "https://thailand-real.estate/property/o82477/",
    "82515": "https://thailand-real.estate/property/o82515/",
    "82494": "https://thailand-real.estate/property/o82494/",
    "82800": "https://thailand-real.estate/property/o82800/",
    "82781": "https://thailand-real.estate/property/o82781/",
    "82769": "https://thailand-real.estate/property/o82769/",
    "82742": "https://thailand-real.estate/property/o82742/",
    "82738": "https://thailand-real.estate/property/o82738/",
    "82722": "https://thailand-real.estate/property/o82722/",
    "82714": "https://thailand-real.estate/property/o82714/",
    "82616": "https://thailand-real.estate/property/o82616/",
    "82638": "https://thailand-real.estate/property/o82638/",
    "82622": "https://thailand-real.estate/property/o82622/",
    "82532": "https://thailand-real.estate/property/o82532/",
    "82524": "https://thailand-real.estate/property/o82524/",
    "82469": "https://thailand-real.estate/property/o82469/",
    "101332": "https://thailand-real.estate/property/o101332/",
    "101433": "https://thailand-real.estate/property/o101433/",
    "101513": "https://thailand-real.estate/property/o101513/",
    "81818": "https://thailand-real.estate/property/o81818/",
    "82675": "https://thailand-real.estate/property/o82675/",
    "100315": "https://thailand-real.estate/property/o100315/",
    "100318": "https://thailand-real.estate/property/o100318/",
    "82713": "https://thailand-real.estate/property/o82713/",
    "82715": "https://thailand-real.estate/property/o82715/",
    "82673": "https://thailand-real.estate/property/o82673/",
    "82516": "https://thailand-real.estate/property/o82516/",
    "82467": "https://thailand-real.estate/property/o82467/",
    "104971": "https://thailand-real.estate/property/o104971/",
    "101443": "https://thailand-real.estate/property/o101443/",
    "101482": "https://thailand-real.estate/property/o101482/",
    "102533": "https://thailand-real.estate/property/o102533/",
    "100216": "https://thailand-real.estate/property/o100216/",
    "100241": "https://thailand-real.estate/property/o100241/",
    "82705": "https://thailand-real.estate/property/o82705/",
    "82761": "https://thailand-real.estate/property/o82761/",
    "82766": "https://thailand-real.estate/property/o82766/",
    "82737": "https://thailand-real.estate/property/o82737/",
    "82707": "https://thailand-real.estate/property/o82707/",
    "82580": "https://thailand-real.estate/property/o82580/",
    "82491": "https://thailand-real.estate/property/o82491/",
    "82463": "https://thailand-real.estate/property/o82463/",
    "101376": "https://thailand-real.estate/property/o101376/",
    "101450": "https://thailand-real.estate/property/o101450/",
    "101460": "https://thailand-real.estate/property/o101460/",
    "100345": "https://thailand-real.estate/property/o100345/",
    "100233": "https://thailand-real.estate/property/o100233/",
    "82606": "https://thailand-real.estate/property/o82606/",
    "82755": "https://thailand-real.estate/property/o82755/",
    "100287": "https://thailand-real.estate/property/o100287/",
    "82792": "https://thailand-real.estate/property/o82792/",
    "82743": "https://thailand-real.estate/property/o82743/",
    "82525": "https://thailand-real.estate/property/o82525/",
    "82695": "https://thailand-real.estate/property/o82695/",
    "100349": "https://thailand-real.estate/property/o100349/",
    "100352": "https://thailand-real.estate/property/o100352/",
    "100354": "https://thailand-real.estate/property/o100354/",
    "100356": "https://thailand-real.estate/property/o100356/",
    "82636": "https://thailand-real.estate/property/o82636/",
    "101436": "https://thailand-real.estate/property/o101436/",
    "101458": "https://thailand-real.estate/property/o101458/",
    "100190": "https://thailand-real.estate/property/o100190/",
    "100205": "https://thailand-real.estate/property/o100205/",
    "100243": "https://thailand-real.estate/property/o100243/",
    "82706": "https://thailand-real.estate/property/o82706/",
    "100371": "https://thailand-real.estate/property/o100371/",
    "100263": "https://thailand-real.estate/property/o100263/",
    "100355": "https://thailand-real.estate/property/o100355/",
    "82620": "https://thailand-real.estate/property/o82620/",
    "82626": "https://thailand-real.estate/property/o82626/",
    "101305": "https://thailand-real.estate/property/o101305/",
    "101370": "https://thailand-real.estate/property/o101370/",
    "101526": "https://thailand-real.estate/property/o101526/",
    "101212": "https://thailand-real.estate/property/o101212/",
    "100269": "https://thailand-real.estate/property/o100269/",
    "82789": "https://thailand-real.estate/property/o82789/",
    "100298": "https://thailand-real.estate/property/o100298/",
    "100340": "https://thailand-real.estate/property/o100340/",
    "82535": "https://thailand-real.estate/property/o82535/",
    "106682": "https://thailand-real.estate/property/o106682/",
    "101541": "https://thailand-real.estate/property/o101541/",
    "101542": "https://thailand-real.estate/property/o101542/",
    "101331": "https://thailand-real.estate/property/o101331/",
    "101380": "https://thailand-real.estate/property/o101380/",
    "101398": "https://thailand-real.estate/property/o101398/",
    "101477": "https://thailand-real.estate/property/o101477/",
    "102151": "https://thailand-real.estate/property/o102151/",
    "100292": "https://thailand-real.estate/property/o100292/",
    "100180": "https://thailand-real.estate/property/o100180/",
    "102529": "https://thailand-real.estate/property/o102529/",
    "100185": "https://thailand-real.estate/property/o100185/",
    "100225": "https://thailand-real.estate/property/o100225/",
    "82791": "https://thailand-real.estate/property/o82791/",
    "82592": "https://thailand-real.estate/property/o82592/",
    "100342": "https://thailand-real.estate/property/o100342/",
    "100353": "https://thailand-real.estate/property/o100353/",
    "101288": "https://thailand-real.estate/property/o101288/",
    "101478": "https://thailand-real.estate/property/o101478/",
    "102528": "https://thailand-real.estate/property/o102528/",
    "102531": "https://thailand-real.estate/property/o102531/",
    "100304": "https://thailand-real.estate/property/o100304/",
    "101211": "https://thailand-real.estate/property/o101211/",
    "100300": "https://thailand-real.estate/property/o100300/",
    "100357": "https://thailand-real.estate/property/o100357/",
    "82501": "https://thailand-real.estate/property/o82501/",
    "82588": "https://thailand-real.estate/property/o82588/",
    "106699": "https://thailand-real.estate/property/o106699/",
    "102933": "https://thailand-real.estate/property/o102933/",
    "102936": "https://thailand-real.estate/property/o102936/",
    "101756": "https://thailand-real.estate/property/o101756/",
    "101309": "https://thailand-real.estate/property/o101309/",
    "101324": "https://thailand-real.estate/property/o101324/",
    "101346": "https://thailand-real.estate/property/o101346/",
    "101435": "https://thailand-real.estate/property/o101435/",
    "101437": "https://thailand-real.estate/property/o101437/",
    "101462": "https://thailand-real.estate/property/o101462/",
    "101479": "https://thailand-real.estate/property/o101479/",
    "102233": "https://thailand-real.estate/property/o102233/",
    "100170": "https://thailand-real.estate/property/o100170/",
    "100171": "https://thailand-real.estate/property/o100171/",
    "102232": "https://thailand-real.estate/property/o102232/",
    "102230": "https://thailand-real.estate/property/o102230/",
    "100187": "https://thailand-real.estate/property/o100187/",
    "100232": "https://thailand-real.estate/property/o100232/",
    "100285": "https://thailand-real.estate/property/o100285/",
    "82756": "https://thailand-real.estate/property/o82756/",
    "100329": "https://thailand-real.estate/property/o100329/",
    "100364": "https://thailand-real.estate/property/o100364/",
    "101823": "https://thailand-real.estate/property/o101823/",
    "102148": "https://thailand-real.estate/property/o102148/",
    "101539": "https://thailand-real.estate/property/o101539/",
    "101310": "https://thailand-real.estate/property/o101310/",
    "101314": "https://thailand-real.estate/property/o101314/",
    "101421": "https://thailand-real.estate/property/o101421/",
    "101455": "https://thailand-real.estate/property/o101455/",
    "101497": "https://thailand-real.estate/property/o101497/",
    "100502": "https://thailand-real.estate/property/o100502/",
    "102527": "https://thailand-real.estate/property/o102527/",
    "102530": "https://thailand-real.estate/property/o102530/",
    "100267": "https://thailand-real.estate/property/o100267/",
    "100024": "https://thailand-real.estate/property/o100024/",
    "101828": "https://thailand-real.estate/property/o101828/",
    "101670": "https://thailand-real.estate/property/o101670/",
    "101452": "https://thailand-real.estate/property/o101452/",
    "101459": "https://thailand-real.estate/property/o101459/",
    "101480": "https://thailand-real.estate/property/o101480/",
    "102234": "https://thailand-real.estate/property/o102234/",
    "100282": "https://thailand-real.estate/property/o100282/",
    "100238": "https://thailand-real.estate/property/o100238/",
    "101199": "https://thailand-real.estate/property/o101199/",
    "100248": "https://thailand-real.estate/property/o100248/",
    "100286": "https://thailand-real.estate/property/o100286/",
    "102931": "https://thailand-real.estate/property/o102931/",
    "101827": "https://thailand-real.estate/property/o101827/",
    "101755": "https://thailand-real.estate/property/o101755/",
    "101306": "https://thailand-real.estate/property/o101306/",
    "101360": "https://thailand-real.estate/property/o101360/",
    "101484": "https://thailand-real.estate/property/o101484/",
    "101495": "https://thailand-real.estate/property/o101495/",
    "102150": "https://thailand-real.estate/property/o102150/",
    "100695": "https://thailand-real.estate/property/o100695/",
    "102235": "https://thailand-real.estate/property/o102235/",
    "102231": "https://thailand-real.estate/property/o102231/",
    "100366": "https://thailand-real.estate/property/o100366/",
    "102526": "https://thailand-real.estate/property/o102526/",
    "101205": "https://thailand-real.estate/property/o101205/",
    "100284": "https://thailand-real.estate/property/o100284/",
    "102937": "https://thailand-real.estate/property/o102937/",
    "101671": "https://thailand-real.estate/property/o101671/",
    "101307": "https://thailand-real.estate/property/o101307/",
    "102149": "https://thailand-real.estate/property/o102149/",
    "105119": "https://thailand-real.estate/property/o105119/",
    "104634": "https://thailand-real.estate/property/o104634/",
    "104745": "https://thailand-real.estate/property/o104745/",
    "104441": "https://thailand-real.estate/property/o104441/",
    "102943": "https://thailand-real.estate/property/o102943/",
    "102947": "https://thailand-real.estate/property/o102947/",
    "101830": "https://thailand-real.estate/property/o101830/",
    "101831": "https://thailand-real.estate/property/o101831/",
    "101543": "https://thailand-real.estate/property/o101543/",
    "100698": "https://thailand-real.estate/property/o100698/",
    "106983": "https://thailand-real.estate/property/o106983/",
    "106698": "https://thailand-real.estate/property/o106698/",
    "106700": "https://thailand-real.estate/property/o106700/",
    "100843": "https://thailand-real.estate/property/o100843/",
    "102532": "https://thailand-real.estate/property/o102532/",
    "100976": "https://thailand-real.estate/property/o100976/",
    "106684": "https://thailand-real.estate/property/o106684/",
    "106697": "https://thailand-real.estate/property/o106697/",
    "106690": "https://thailand-real.estate/property/o106690/",
    "106694": "https://thailand-real.estate/property/o106694/",
    "106692": "https://thailand-real.estate/property/o106692/",
    "106693": "https://thailand-real.estate/property/o106693/",
    "106691": "https://thailand-real.estate/property/o106691/",
    "106695": "https://thailand-real.estate/property/o106695/",
    "106696": "https://thailand-real.estate/property/o106696/",
    "113371": "https://thailand-real.estate/property/o113371/",
    "113378": "https://thailand-real.estate/property/o113378/",
    "112339": "https://thailand-real.estate/property/o112339/",
    "113361": "https://thailand-real.estate/property/o113361/",
    "112338": "https://thailand-real.estate/property/o112338/",
    "112423": "https://thailand-real.estate/property/o112423/",
    "112431": "https://thailand-real.estate/property/o112431/",
    "112434": "https://thailand-real.estate/property/o112434/",
    "112435": "https://thailand-real.estate/property/o112435/",
    "113358": "https://thailand-real.estate/property/o113358/",
    "113359": "https://thailand-real.estate/property/o113359/",
    "113362": "https://thailand-real.estate/property/o113362/",
    "113363": "https://thailand-real.estate/property/o113363/",
    "113377": "https://thailand-real.estate/property/o113377/",
    "112326": "https://thailand-real.estate/property/o112326/",
    "112327": "https://thailand-real.estate/property/o112327/",
    "112336": "https://thailand-real.estate/property/o112336/",
    "112342": "https://thailand-real.estate/property/o112342/",
    "112347": "https://thailand-real.estate/property/o112347/",
    "112430": "https://thailand-real.estate/property/o112430/",
    "112441": "https://thailand-real.estate/property/o112441/",
    "112321": "https://thailand-real.estate/property/o112321/",
    "112324": "https://thailand-real.estate/property/o112324/",
    "112343": "https://thailand-real.estate/property/o112343/",
    "112436": "https://thailand-real.estate/property/o112436/",
    "112772": "https://thailand-real.estate/property/o112772/",
    "113429": "https://thailand-real.estate/property/o113429/",
    "112335": "https://thailand-real.estate/property/o112335/",
    "112381": "https://thailand-real.estate/property/o112381/",
    "112388": "https://thailand-real.estate/property/o112388/",
    "112391": "https://thailand-real.estate/property/o112391/",
    "112402": "https://thailand-real.estate/property/o112402/",
    "112639": "https://thailand-real.estate/property/o112639/",
    "112814": "https://thailand-real.estate/property/o112814/",
    "113114": "https://thailand-real.estate/property/o113114/",
    "112357": "https://thailand-real.estate/property/o112357/",
    "112395": "https://thailand-real.estate/property/o112395/",
    "112399": "https://thailand-real.estate/property/o112399/",
    "112432": "https://thailand-real.estate/property/o112432/",
    "112500": "https://thailand-real.estate/property/o112500/",
    "112622": "https://thailand-real.estate/property/o112622/",
    "112635": "https://thailand-real.estate/property/o112635/",
    "112769": "https://thailand-real.estate/property/o112769/",
    "113385": "https://thailand-real.estate/property/o113385/",
    "113455": "https://thailand-real.estate/property/o113455/",
    "113435": "https://thailand-real.estate/property/o113435/",
    "113476": "https://thailand-real.estate/property/o113476/",
    "113446": "https://thailand-real.estate/property/o113446/",
    "113447": "https://thailand-real.estate/property/o113447/",
    "113448": "https://thailand-real.estate/property/o113448/",
    "113461": "https://thailand-real.estate/property/o113461/",
    "113356": "https://thailand-real.estate/property/o113356/",
    "113360": "https://thailand-real.estate/property/o113360/",
    "112405": "https://thailand-real.estate/property/o112405/",
    "112454": "https://thailand-real.estate/property/o112454/",
    "112457": "https://thailand-real.estate/property/o112457/",
    "112458": "https://thailand-real.estate/property/o112458/",
    "112472": "https://thailand-real.estate/property/o112472/",
    "112473": "https://thailand-real.estate/property/o112473/",
    "112486": "https://thailand-real.estate/property/o112486/",
    "112544": "https://thailand-real.estate/property/o112544/",
    "112554": "https://thailand-real.estate/property/o112554/",
    "112582": "https://thailand-real.estate/property/o112582/",
    "112591": "https://thailand-real.estate/property/o112591/",
    "112617": "https://thailand-real.estate/property/o112617/",
    "112623": "https://thailand-real.estate/property/o112623/",
    "112631": "https://thailand-real.estate/property/o112631/",
    "112682": "https://thailand-real.estate/property/o112682/",
    "112737": "https://thailand-real.estate/property/o112737/",
    "112739": "https://thailand-real.estate/property/o112739/",
    "112743": "https://thailand-real.estate/property/o112743/",
    "112744": "https://thailand-real.estate/property/o112744/",
    "112748": "https://thailand-real.estate/property/o112748/",
    "112753": "https://thailand-real.estate/property/o112753/",
    "112754": "https://thailand-real.estate/property/o112754/",
    "112757": "https://thailand-real.estate/property/o112757/",
    "112760": "https://thailand-real.estate/property/o112760/",
    "112762": "https://thailand-real.estate/property/o112762/",
    "112763": "https://thailand-real.estate/property/o112763/",
    "112764": "https://thailand-real.estate/property/o112764/",
    "112768": "https://thailand-real.estate/property/o112768/",
    "112771": "https://thailand-real.estate/property/o112771/",
    "112784": "https://thailand-real.estate/property/o112784/",
    "112902": "https://thailand-real.estate/property/o112902/",
    "112998": "https://thailand-real.estate/property/o112998/",
    "113041": "https://thailand-real.estate/property/o113041/",
    "113393": "https://thailand-real.estate/property/o113393/",
    "113469": "https://thailand-real.estate/property/o113469/",
    "113392": "https://thailand-real.estate/property/o113392/",
    "113394": "https://thailand-real.estate/property/o113394/",
    "113396": "https://thailand-real.estate/property/o113396/",
    "113397": "https://thailand-real.estate/property/o113397/",
    "113405": "https://thailand-real.estate/property/o113405/",
    "113415": "https://thailand-real.estate/property/o113415/",
    "113416": "https://thailand-real.estate/property/o113416/",
    "113425": "https://thailand-real.estate/property/o113425/",
    "113445": "https://thailand-real.estate/property/o113445/",
    "113486": "https://thailand-real.estate/property/o113486/",
    "113462": "https://thailand-real.estate/property/o113462/",
    "115156": "https://thailand-real.estate/property/o115156/",
    "112409": "https://thailand-real.estate/property/o112409/",
    "112415": "https://thailand-real.estate/property/o112415/",
    "112459": "https://thailand-real.estate/property/o112459/",
    "112494": "https://thailand-real.estate/property/o112494/",
    "112496": "https://thailand-real.estate/property/o112496/",
    "112561": "https://thailand-real.estate/property/o112561/",
    "112580": "https://thailand-real.estate/property/o112580/",
    "112581": "https://thailand-real.estate/property/o112581/",
    "112585": "https://thailand-real.estate/property/o112585/",
    "112588": "https://thailand-real.estate/property/o112588/",
    "112596": "https://thailand-real.estate/property/o112596/",
    "112742": "https://thailand-real.estate/property/o112742/",
    "112865": "https://thailand-real.estate/property/o112865/",
    "112866": "https://thailand-real.estate/property/o112866/",
    "112867": "https://thailand-real.estate/property/o112867/",
    "112914": "https://thailand-real.estate/property/o112914/",
    "112953": "https://thailand-real.estate/property/o112953/",
    "112992": "https://thailand-real.estate/property/o112992/",
    "113389": "https://thailand-real.estate/property/o113389/",
    "112353": "https://thailand-real.estate/property/o112353/",
    "112360": "https://thailand-real.estate/property/o112360/",
    "112361": "https://thailand-real.estate/property/o112361/",
    "112365": "https://thailand-real.estate/property/o112365/",
    "112371": "https://thailand-real.estate/property/o112371/",
    "112375": "https://thailand-real.estate/property/o112375/",
    "112505": "https://thailand-real.estate/property/o112505/",
    "112520": "https://thailand-real.estate/property/o112520/",
    "112523": "https://thailand-real.estate/property/o112523/",
    "112542": "https://thailand-real.estate/property/o112542/",
    "112543": "https://thailand-real.estate/property/o112543/",
    "112545": "https://thailand-real.estate/property/o112545/",
    "112547": "https://thailand-real.estate/property/o112547/",
    "112551": "https://thailand-real.estate/property/o112551/",
    "112553": "https://thailand-real.estate/property/o112553/",
    "112616": "https://thailand-real.estate/property/o112616/",
    "112624": "https://thailand-real.estate/property/o112624/",
    "112625": "https://thailand-real.estate/property/o112625/",
    "112626": "https://thailand-real.estate/property/o112626/",
    "112627": "https://thailand-real.estate/property/o112627/",
    "112629": "https://thailand-real.estate/property/o112629/",
    "112630": "https://thailand-real.estate/property/o112630/",
    "112633": "https://thailand-real.estate/property/o112633/",
    "112636": "https://thailand-real.estate/property/o112636/",
    "112637": "https://thailand-real.estate/property/o112637/",
    "112638": "https://thailand-real.estate/property/o112638/",
    "112641": "https://thailand-real.estate/property/o112641/",
    "112642": "https://thailand-real.estate/property/o112642/",
    "112643": "https://thailand-real.estate/property/o112643/",
    "112647": "https://thailand-real.estate/property/o112647/",
    "112655": "https://thailand-real.estate/property/o112655/",
    "112657": "https://thailand-real.estate/property/o112657/",
    "112659": "https://thailand-real.estate/property/o112659/",
    "112660": "https://thailand-real.estate/property/o112660/",
    "112661": "https://thailand-real.estate/property/o112661/",
    "112662": "https://thailand-real.estate/property/o112662/",
    "112663": "https://thailand-real.estate/property/o112663/",
    "112680": "https://thailand-real.estate/property/o112680/",
    "112681": "https://thailand-real.estate/property/o112681/",
    "112699": "https://thailand-real.estate/property/o112699/",
    "112715": "https://thailand-real.estate/property/o112715/",
    "112725": "https://thailand-real.estate/property/o112725/",
    "112728": "https://thailand-real.estate/property/o112728/",
    "112729": "https://thailand-real.estate/property/o112729/",
    "112732": "https://thailand-real.estate/property/o112732/",
    "112734": "https://thailand-real.estate/property/o112734/",
    "112735": "https://thailand-real.estate/property/o112735/",
    "112778": "https://thailand-real.estate/property/o112778/",
    "112792": "https://thailand-real.estate/property/o112792/",
    "112936": "https://thailand-real.estate/property/o112936/",
    "112937": "https://thailand-real.estate/property/o112937/",
    "112939": "https://thailand-real.estate/property/o112939/",
    "112969": "https://thailand-real.estate/property/o112969/",
    "112988": "https://thailand-real.estate/property/o112988/",
    "112989": "https://thailand-real.estate/property/o112989/",
    "112990": "https://thailand-real.estate/property/o112990/",
    "112991": "https://thailand-real.estate/property/o112991/",
    "112993": "https://thailand-real.estate/property/o112993/",
    "112997": "https://thailand-real.estate/property/o112997/",
    "113000": "https://thailand-real.estate/property/o113000/",
    "113001": "https://thailand-real.estate/property/o113001/",
    "113433": "https://thailand-real.estate/property/o113433/",
    "113424": "https://thailand-real.estate/property/o113424/",
    "113428": "https://thailand-real.estate/property/o113428/",
    "113436": "https://thailand-real.estate/property/o113436/",
    "113449": "https://thailand-real.estate/property/o113449/",
    "113451": "https://thailand-real.estate/property/o113451/",
    "113450": "https://thailand-real.estate/property/o113450/",
    "113452": "https://thailand-real.estate/property/o113452/",
    "113453": "https://thailand-real.estate/property/o113453/",
    "113467": "https://thailand-real.estate/property/o113467/",
    "113466": "https://thailand-real.estate/property/o113466/",
    "113465": "https://thailand-real.estate/property/o113465/",
    "113464": "https://thailand-real.estate/property/o113464/",
    "113463": "https://thailand-real.estate/property/o113463/"
}